.gitignore
AUTHORS
LICENSE
NOTICE
README
requirements.txt
setup.py
test.txt
docs/.buildinfo
docs/genindex.html
docs/index.html
docs/media_and_templates.html
docs/modindex.html
docs/objects.inv
docs/search.html
docs/searchindex.js
docs/settings.html
docs/templatetags.html
docs/_sources/index.txt
docs/_sources/media_and_templates.txt
docs/_sources/settings.txt
docs/_sources/templatetags.txt
docs/_sources/reference/index.txt
docs/_sources/reference/models.txt
docs/_static/basic.css
docs/_static/breadcrumb_background.png
docs/_static/default.css
docs/_static/doctools.js
docs/_static/documentation.png
docs/_static/file.png
docs/_static/header_sm_mid.png
docs/_static/jquery.js
docs/_static/minus.png
docs/_static/plus.png
docs/_static/pygments.css
docs/_static/scrn1.png
docs/_static/scrn2.png
docs/_static/searchfield_leftcap.png
docs/_static/searchfield_repeat.png
docs/_static/searchfield_rightcap.png
docs/_static/searchtools.js
docs/_static/title_background.png
docs/_static/toc.js
docs/_static/triangle_closed.png
docs/_static/triangle_left.png
docs/_static/triangle_open.png
docs/reference/index.html
docs/reference/models.html
docs_src/Makefile
docs_src/conf.py
docs_src/index.rst
docs_src/make.bat
docs_src/media_and_templates.rst
docs_src/settings.rst
docs_src/templatetags.rst
docs_src/tinymce_and_filebrowsing.rst
docs_src/_build/doctrees/environment.pickle
docs_src/_build/doctrees/index.doctree
docs_src/_build/doctrees/media_and_templates.doctree
docs_src/_build/doctrees/settings.doctree
docs_src/_build/doctrees/templatetags.doctree
docs_src/_build/doctrees/reference/index.doctree
docs_src/_build/doctrees/reference/models.doctree
docs_src/_ext/djangodocumentor.py
docs_src/_static/breadcrumb_background.png
docs_src/_static/default.css
docs_src/_static/documentation.png
docs_src/_static/header_sm_mid.png
docs_src/_static/scrn1.png
docs_src/_static/scrn2.png
docs_src/_static/searchfield_leftcap.png
docs_src/_static/searchfield_repeat.png
massmedia.egg-info/PKG-INFO
massmedia.egg-info/SOURCES.txt
massmedia.egg-info/dependency_links.txt
massmedia.egg-info/requires.txt
massmedia.egg-info/top_level.txt
