Metadata-Version: 1.0
Name: massmedia
Version: 0.6.4
Summary: Allows for site staff can upload and edit the media files through the site, and the filesystem is maintained in the background.
Home-page: http://opensource.washingtontimes.com/projects/django-massmedia/
Author: Justin Quick
Author-email: jquick@washingtontimes.com
License: UNKNOWN
Platform: UNKNOWN
